{"resource":"playbyplay","parameters":{"GameID":"0041400175","StartPeriod":0,"EndPeriod":14},"resultSets":[{"name":"PlayByPlay","headers":["GAME_ID","EVENTNUM","EVENTMSGTYPE","EVENTMSGACTIONTYPE","PERIOD","WCTIMESTRING","PCTIMESTRING","HOMEDESCRIPTION","NEUTRALDESCRIPTION","VISITORDESCRIPTION","SCORE","SCOREMARGIN"],"rowSet":[["0041400175",0,12,0,1,"9:47 PM","12:00",null,null,null,null,null],["0041400175",1,10,0,1,"9:47 PM","12:00","Jump Ball Gasol vs. Lopez: Tip to Randolph",null,null,null,null],["0041400175",2,2,1,1,"9:47 PM","11:38","MISS Allen 20' Jump Shot",null,null,null,null],["0041400175",3,4,0,1,"9:47 PM","11:37",null,null,"Aldridge REBOUND (Off:0 Def:1)",null,null],["0041400175",4,5,1,1,"9:47 PM","11:31",null,null,"Lillard Bad Pass Turnover (P1.T1)",null,null],["0041400175",5,1,73,1,"9:48 PM","11:18","Randolph 1' Driving Reverse Layup (2 PTS)",null,null,"0 - 2","2"],["0041400175",6,5,2,1,"9:48 PM","11:04","Allen STEAL (1 STL)",null,"Afflalo Lost Ball Turnover (P1.T2)",null,null],["0041400175",7,1,1,1,"9:48 PM","10:54","Randolph 17' Jump Shot (4 PTS) (Calathes 1 AST)",null,null,"0 - 4","4"],["0041400175",9,2,1,1,"9:49 PM","10:38",null,null,"MISS Lillard 21' Jump Shot",null,null],["0041400175",10,4,0,1,"9:49 PM","10:37","Randolph REBOUND (Off:0 Def:1)",null,null,null,null],["0041400175",11,7,5,1,"9:49 PM","10:28",null,null,"Batum Violation:Kicked Ball (.)",null,null],["0041400175",12,1,1,1,"9:49 PM","10:19","Randolph 19' Jump Shot (6 PTS) (Lee 1 AST)",null,null,"0 - 6","6"],["0041400175",13,6,1,1,"9:49 PM","10:12","Randolph P.FOUL (P1.T1) (K.Mauer)",null,null,null,null],["0041400175",14,2,1,1,"9:50 PM","10:02","Allen BLOCK (1 BLK)",null,"MISS Aldridge 8' Jump Shot",null,null],["0041400175",15,4,0,1,"9:50 PM","10:00","Randolph REBOUND (Off:0 Def:2)",null,null,null,null],["0041400175",16,5,1,1,"9:50 PM","9:53","Randolph Bad Pass Turnover (P1.T1)",null,null,null,null],["0041400175",17,2,63,1,"9:50 PM","9:37",null,null,"MISS Afflalo 7' Fadeaway Jumper",null,null],["0041400175",18,4,0,1,"9:50 PM","9:35","Gasol REBOUND (Off:0 Def:1)",null,null,null,null],["0041400175",19,1,79,1,"9:50 PM","9:26","Lee 19' Pullup Jump Shot (2 PTS)",null,null,"0 - 8","8"],["0041400175",21,9,1,1,"9:51 PM","9:25",null,null,"Trail Blazers Timeout: Regular (Reg.1 Short 0)",null,null],["0041400175",22,5,1,1,"9:54 PM","9:03","Lee STEAL (1 STL)",null,"Aldridge Bad Pass Turnover (P1.T3)",null,null],["0041400175",23,1,79,1,"9:54 PM","8:58","Lee 13' Pullup Jump Shot (4 PTS)",null,null,"0 - 10","10"],["0041400175",24,2,1,1,"9:55 PM","8:43",null,null,"MISS Lillard 25' 3PT Jump Shot",null,null],["0041400175",25,4,0,1,"9:55 PM","8:42","Allen REBOUND (Off:0 Def:1)",null,null,null,null],["0041400175",26,2,1,1,"9:55 PM","8:22","MISS Calathes 24' 3PT Jump Shot",null,"Lillard BLOCK (1 BLK)",null,null],["0041400175",27,4,0,1,"9:55 PM","8:20",null,null,"Batum REBOUND (Off:0 Def:1)",null,null],["0041400175",28,6,2,1,"9:55 PM","8:06","Lee S.FOUL (P1.T2) (B.Forte)",null,null,null,null],["0041400175",29,3,11,1,"9:55 PM","8:06",null,null,"MISS Batum Free Throw 1 of 2",null,null],["0041400175",31,4,0,1,"9:56 PM","8:06",null,null,"Trail Blazers Rebound",null,null],["0041400175",30,3,12,1,"9:56 PM","8:06",null,null,"Batum Free Throw 2 of 2 (1 PTS)","1 - 10","9"],["0041400175",33,6,1,1,"9:56 PM","7:52",null,null,"Lopez P.FOUL (P1.T1) (B.Forte)",null,null],["0041400175",34,1,1,1,"9:57 PM","7:42","Allen  3PT Jump Shot (3 PTS) (Calathes 2 AST)",null,null,"1 - 13","12"],["0041400175",35,1,42,1,"9:57 PM","7:30",null,null,"Lillard 1' Driving Layup (2 PTS)","3 - 13","10"],["0041400175",36,1,1,1,"9:57 PM","7:06","Randolph 20' Jump Shot (8 PTS) (Gasol 1 AST)",null,null,"3 - 15","12"],["0041400175",37,1,1,1,"9:57 PM","6:54",null,null,"Batum 26' 3PT Jump Shot (4 PTS) (Aldridge 1 AST)","6 - 15","9"],["0041400175",39,5,40,1,"9:58 PM","6:38","Calathes Out of Bounds Lost Ball Turnover (P1.T2)",null,null,null,null],["0041400175",40,8,0,1,"9:58 PM","6:38",null,null,"SUB: Leonard FOR Afflalo",null,null],["0041400175",41,8,0,1,"9:58 PM","6:38",null,null,"SUB: McCollum FOR Lopez",null,null],["0041400175",42,5,1,1,"9:58 PM","6:17","Allen STEAL (2 STL)",null,"Lillard Bad Pass Turnover (P2.T4)",null,null],["0041400175",43,6,2,1,"9:59 PM","6:03",null,null,"Leonard S.FOUL (P1.T2) (E.Malloy)",null,null],["0041400175",44,3,11,1,"9:59 PM","6:03","Allen Free Throw 1 of 2 (4 PTS)",null,null,"6 - 16","10"],["0041400175",46,3,12,1,"9:59 PM","6:03","MISS Allen Free Throw 2 of 2",null,null,null,null],["0041400175",47,4,0,1,"10:00 PM","6:02",null,null,"Batum REBOUND (Off:0 Def:2)",null,null],["0041400175",48,2,1,1,"10:00 PM","5:45",null,null,"MISS Batum 26' 3PT Jump Shot",null,null],["0041400175",49,4,0,1,"10:00 PM","5:44","Gasol REBOUND (Off:0 Def:2)",null,null,null,null],["0041400175",51,5,13,1,"10:00 PM","5:24","Gasol Backcourt Turnover (P1.T3)",null,null,null,null],["0041400175",52,1,42,1,"10:01 PM","5:17",null,null,"Lillard 1' Driving Layup (4 PTS)","8 - 16","8"],["0041400175",53,1,1,1,"10:01 PM","4:53","Gasol 10' Jump Shot (2 PTS) (Calathes 3 AST)",null,null,"8 - 18","10"],["0041400175",54,2,5,1,"10:01 PM","4:44","Gasol BLOCK (1 BLK)",null,"MISS Lillard 1' Layup",null,null],["0041400175",55,4,0,1,"10:02 PM","4:40","Gasol REBOUND (Off:0 Def:3)",null,null,null,null],["0041400175",56,2,47,1,"10:02 PM","4:30","MISS Randolph 6' Turnaround Jump Shot",null,"Aldridge BLOCK (1 BLK)",null,null],["0041400175",57,4,0,1,"10:02 PM","4:30","GRIZZLIES Rebound",null,null,null,null],["0041400175",58,8,0,1,"10:02 PM","4:30","SUB: Udrih FOR Calathes",null,null,null,null],["0041400175",59,2,47,1,"10:02 PM","4:21","MISS Randolph 6' Turnaround Jump Shot",null,null,null,null],["0041400175",60,4,0,1,"10:02 PM","4:19","Allen REBOUND (Off:1 Def:1)",null,null,null,null],["0041400175",61,2,5,1,"10:02 PM","4:17","MISS Randolph 3' Layup",null,null,null,null],["0041400175",62,4,0,1,"10:02 PM","4:15",null,null,"McCollum REBOUND (Off:0 Def:1)",null,null],["0041400175",63,1,42,1,"10:03 PM","4:09",null,null,"McCollum 2' Driving Layup (2 PTS)","10 - 18","8"],["0041400175",65,9,1,1,"10:03 PM","4:02","GRIZZLIES Timeout: Regular (Full 1 Short 0)",null,null,null,null],["0041400175",66,8,0,1,"10:06 PM","4:02","SUB: Green FOR Allen",null,null,null,null],["0041400175",69,2,63,1,"10:07 PM","3:45","MISS Green 14' Fadeaway Jumper",null,null,null,null],["0041400175",70,4,0,1,"10:07 PM","3:44","GRIZZLIES Rebound",null,null,null,null],["0041400175",71,6,3,1,"10:07 PM","3:44",null,null,"Leonard L.B.FOUL (P2.T3) (B.Forte)",null,null],["0041400175",72,2,1,1,"10:07 PM","3:34","MISS Udrih 26' 3PT Jump Shot",null,null,null,null],["0041400175",73,4,0,1,"10:07 PM","3:33",null,null,"Lillard REBOUND (Off:0 Def:1)",null,null],["0041400175",74,2,47,1,"10:08 PM","3:17",null,null,"MISS Aldridge 4' Turnaround Jump Shot",null,null],["0041400175",75,4,0,1,"10:08 PM","3:15",null,null,"Leonard REBOUND (Off:1 Def:0)",null,null],["0041400175",76,6,1,1,"10:08 PM","3:15","Gasol P.FOUL (P1.T3) (E.Malloy)",null,null,null,null],["0041400175",77,1,42,1,"10:08 PM","3:12",null,null,"Lillard 1' Driving Layup (6 PTS)","12 - 18","6"],["0041400175",78,6,2,1,"10:08 PM","3:12","Udrih S.FOUL (P1.T4) (K.Mauer)",null,null,null,null],["0041400175",79,8,0,1,"10:08 PM","3:12",null,null,"SUB: Lopez FOR Aldridge",null,null],["0041400175",80,3,10,1,"10:09 PM","3:12",null,null,"Lillard Free Throw 1 of 1 (7 PTS)","13 - 18","5"],["0041400175",82,2,1,1,"10:09 PM","2:57","MISS Lee 25' 3PT Jump Shot",null,null,null,null],["0041400175",83,4,0,1,"10:09 PM","2:56",null,null,"Lopez REBOUND (Off:0 Def:1)",null,null],["0041400175",84,6,1,1,"10:09 PM","2:50","Green P.FOUL (P1.PN) (E.Malloy)",null,null,null,null],["0041400175",85,3,11,1,"10:10 PM","2:50",null,null,"Lillard Free Throw 1 of 2 (8 PTS)","14 - 18","4"],["0041400175",87,3,12,1,"10:10 PM","2:50",null,null,"Lillard Free Throw 2 of 2 (9 PTS)","15 - 18","3"],["0041400175",89,1,3,1,"10:10 PM","2:30","Gasol 6' Hook Shot (4 PTS)",null,null,"15 - 20","5"],["0041400175",90,1,84,1,"10:10 PM","2:14",null,null,"McCollum 7' Running Bank Shot (4 PTS)","17 - 20","3"],["0041400175",91,2,46,1,"10:11 PM","1:55","MISS Randolph 5' Running Jump Shot",null,null,null,null],["0041400175",92,4,0,1,"10:11 PM","1:53",null,null,"Lopez REBOUND (Off:0 Def:2)",null,null],["0041400175",93,2,80,1,"10:11 PM","1:41",null,null,"MISS Lillard  3PT Step Back Jump Shot",null,null],["0041400175",94,4,0,1,"10:11 PM","1:39","Udrih REBOUND (Off:0 Def:1)",null,null,null,null],["0041400175",95,2,1,1,"10:11 PM","1:34","MISS Green 26' 3PT Jump Shot",null,null,null,null],["0041400175",96,4,0,1,"10:11 PM","1:32",null,null,"Batum REBOUND (Off:0 Def:3)",null,null],["0041400175",97,2,1,1,"10:11 PM","1:27",null,null,"MISS Batum 26' 3PT Jump Shot",null,null],["0041400175",98,4,0,1,"10:11 PM","1:25","Green REBOUND (Off:0 Def:1)",null,null,null,null],["0041400175",99,6,26,1,"10:11 PM","1:22","Green Offensive Charge Foul (P2.PN) (E.Malloy)",null,null,null,null],["0041400175",100,5,5,1,"10:11 PM","1:22","Green Foul Turnover (P1.T4)",null,null,null,null],["0041400175",101,8,0,1,"10:12 PM","1:22","SUB: Carter FOR Randolph",null,null,null,null],["0041400175",102,6,2,1,"10:12 PM","1:09","Udrih S.FOUL (P2.PN) (K.Mauer)",null,null,null,null],["0041400175",103,3,11,1,"10:12 PM","1:09",null,null,"MISS McCollum Free Throw 1 of 2",null,null],["0041400175",105,4,0,1,"10:13 PM","1:09",null,null,"Trail Blazers Rebound",null,null],["0041400175",104,8,0,1,"10:13 PM","1:09",null,null,"SUB: Blake FOR Lillard",null,null],["0041400175",106,3,12,1,"10:13 PM","1:09",null,null,"McCollum Free Throw 2 of 2 (5 PTS)","18 - 20","2"],["0041400175",108,2,56,1,"10:13 PM","0:50","MISS Gasol 8' Running Hook Shot",null,"Lopez BLOCK (1 BLK)",null,null],["0041400175",109,4,0,1,"10:13 PM","0:48",null,null,"Lopez REBOUND (Off:0 Def:3)",null,null],["0041400175",110,1,79,1,"10:14 PM","0:32",null,null,"McCollum 22' Pullup Jump Shot (7 PTS)","20 - 20","TIE"],["0041400175",111,2,1,1,"10:14 PM","0:12","MISS Green 17' Jump Shot",null,null,null,null],["0041400175",112,4,0,1,"10:14 PM","0:12",null,null,"McCollum REBOUND (Off:0 Def:2)",null,null],["0041400175",113,2,80,1,"10:14 PM","0:00",null,null,"MISS McCollum 21' Step Back Jump Shot",null,null],["0041400175",115,4,0,1,"10:14 PM","0:00",null,null,"Trail Blazers Rebound",null,null],["0041400175",114,18,0,1,"10:14 PM","0:00",null,null,null,null,null],["0041400175",117,13,0,1,"10:14 PM","0:00",null,null,null,"20 - 20","TIE"],["0041400175",119,12,0,2,"10:18 PM","12:00",null,null,null,"20 - 20","TIE"],["0041400175",120,2,1,2,"10:18 PM","11:43",null,null,"MISS Blake 26' 3PT Jump Shot",null,null],["0041400175",121,4,0,2,"10:18 PM","11:42","Green REBOUND (Off:0 Def:2)",null,null,null,null],["0041400175",122,2,3,2,"10:18 PM","11:27","MISS Koufos 8' Hook Shot",null,null,null,null],["0041400175",123,4,0,2,"10:18 PM","11:25",null,null,"Kaman REBOUND (Off:0 Def:1)",null,null],["0041400175",124,2,1,2,"10:19 PM","11:16",null,null,"MISS Aldridge 15' Jump Shot",null,null],["0041400175",125,4,0,2,"10:19 PM","11:15","Koufos REBOUND (Off:0 Def:1)",null,null,null,null],["0041400175",126,6,2,2,"10:19 PM","11:06",null,null,"McCollum S.FOUL (P1.T1) (K.Mauer)",null,null],["0041400175",127,3,11,2,"10:19 PM","11:06","Udrih Free Throw 1 of 2 (1 PTS)",null,null,"20 - 21","1"],["0041400175",129,3,12,2,"10:19 PM","11:06","Udrih Free Throw 2 of 2 (2 PTS)",null,null,"20 - 22","2"],["0041400175",131,1,5,2,"10:20 PM","10:46",null,null,"Aldridge 1' Layup (2 PTS)","22 - 22","TIE"],["0041400175",132,2,63,2,"10:20 PM","10:26","MISS Carter 18' Fadeaway Jumper",null,null,null,null],["0041400175",133,4,0,2,"10:20 PM","10:24",null,null,"Aldridge REBOUND (Off:0 Def:2)",null,null],["0041400175",134,1,1,2,"10:20 PM","10:17",null,null,"Blake 16' Jump Shot (2 PTS)","24 - 22","-2"],["0041400175",135,1,1,2,"10:21 PM","9:58","Udrih 19' Jump Shot (4 PTS)",null,null,"24 - 24","TIE"],["0041400175",136,6,14,2,"10:21 PM","9:51","Allen FLAGRANT.FOUL.TYPE1 (P1.T1) (K.Mauer)",null,null,null,null],["0041400175",137,18,0,2,"10:21 PM","9:51",null,null,null,null,null],["0041400175",138,3,18,2,"10:22 PM","9:51",null,null,"MISS McCollum Free Throw Flagrant 1 of 2",null,null],["0041400175",139,4,1,2,"10:22 PM","9:51",null,null,"Trail Blazers Rebound",null,null],["0041400175",140,8,0,2,"10:22 PM","9:51","SUB: Calathes FOR Udrih",null,null,null,null],["0041400175",141,8,0,2,"10:22 PM","9:51","SUB: Randolph FOR Green",null,null,null,null],["0041400175",142,3,19,2,"10:22 PM","9:51",null,null,"McCollum Free Throw Flagrant 2 of 2 (8 PTS)","25 - 24","-1"],["0041400175",144,2,5,2,"10:23 PM","9:42","Carter BLOCK (1 BLK)",null,"MISS Afflalo 1' Layup",null,null],["0041400175",145,4,0,2,"10:23 PM","9:40","Calathes REBOUND (Off:0 Def:1)",null,null,null,null],["0041400175",146,5,11,2,"10:23 PM","9:19","GRIZZLIES Turnover: Shot Clock (T#5)",null,null,null,null],["0041400175",147,1,1,2,"10:24 PM","9:00",null,null,"McCollum 25' 3PT Jump Shot (11 PTS) (Blake 1 AST)","28 - 24","-4"],["0041400175",148,9,1,2,"10:24 PM","8:47","GRIZZLIES Timeout: Regular (Full 2 Short 0)",null,null,null,null],["0041400175",150,1,46,2,"10:28 PM","8:36","Randolph 4' Running Jump Shot (10 PTS) (Calathes 4 AST)",null,null,"28 - 26","-2"],["0041400175",151,5,1,2,"10:28 PM","8:20","Randolph STEAL (1 STL)",null,"Kaman Bad Pass Turnover (P1.T5)",null,null],["0041400175",152,2,1,2,"10:28 PM","8:06","MISS Randolph 17' Jump Shot",null,null,null,null],["0041400175",153,4,0,2,"10:28 PM","8:06","Koufos REBOUND (Off:1 Def:1)",null,null,null,null],["0041400175",154,2,5,2,"10:28 PM","7:53","MISS Calathes 1' Layup",null,null,null,null],["0041400175",156,4,0,2,"10:28 PM","7:51","Koufos REBOUND (Off:2 Def:1)",null,null,null,null],["0041400175",155,2,4,2,"10:28 PM","7:51","MISS Koufos 1' Tip Shot",null,null,null,null],["0041400175",157,4,0,2,"10:28 PM","7:50","Koufos REBOUND (Off:3 Def:1)",null,null,null,null],["0041400175",158,2,1,2,"10:28 PM","7:45","MISS Calathes  3PT Jump Shot",null,null,null,null],["0041400175",159,4,0,2,"10:28 PM","7:44",null,null,"Kaman REBOUND (Off:0 Def:2)",null,null],["0041400175",160,2,1,2,"10:29 PM","7:34",null,null,"MISS Blake 21' Jump Shot",null,null],["0041400175",161,4,0,2,"10:29 PM","7:32","Koufos REBOUND (Off:3 Def:2)",null,null,null,null],["0041400175",162,1,42,2,"10:29 PM","7:18","Carter 2' Driving Layup (2 PTS)",null,null,"28 - 28","TIE"],["0041400175",163,6,2,2,"10:29 PM","7:18",null,null,"Kaman S.FOUL (P1.T2) (E.Malloy)",null,null],["0041400175",164,8,0,2,"10:29 PM","7:18",null,null,"SUB: Batum FOR Blake",null,null],["0041400175",165,8,0,2,"10:29 PM","7:18",null,null,"SUB: Lillard FOR McCollum",null,null],["0041400175",166,3,10,2,"10:29 PM","7:18","Carter Free Throw 1 of 1 (3 PTS)",null,null,"28 - 29","1"],["0041400175",168,1,46,2,"10:30 PM","6:59",null,null,"Aldridge 11' Running Jump Shot (4 PTS)","30 - 29","-1"],["0041400175",169,2,1,2,"10:30 PM","6:46","MISS Carter 26' 3PT Jump Shot",null,null,null,null],["0041400175",170,4,0,2,"10:30 PM","6:45","Koufos REBOUND (Off:4 Def:2)",null,null,null,null],["0041400175",171,2,46,2,"10:30 PM","6:40","MISS Calathes 7' Running Jump Shot",null,null,null,null],["0041400175",172,4,0,2,"10:30 PM","6:37",null,null,"Aldridge REBOUND (Off:0 Def:3)",null,null],["0041400175",173,6,28,2,"10:30 PM","6:33","Calathes Personal Take Foul (P1.T2) (K.Mauer)",null,null,null,null],["0041400175",174,8,0,2,"10:30 PM","6:33",null,null,"SUB: Leonard FOR Kaman",null,null],["0041400175",175,5,2,2,"10:31 PM","6:28","Koufos STEAL (1 STL)",null,"Lillard Lost Ball Turnover (P3.T6)",null,null],["0041400175",176,2,1,2,"10:31 PM","6:20","MISS Carter 26' 3PT Jump Shot",null,null,null,null],["0041400175",177,4,0,2,"10:31 PM","6:18","Carter REBOUND (Off:1 Def:0)",null,null,null,null],["0041400175",178,1,44,2,"10:31 PM","6:15","Allen 1' Reverse Layup (6 PTS) (Carter 1 AST)",null,null,"30 - 31","1"],["0041400175",180,9,1,2,"10:31 PM","6:13",null,null,"Trail Blazers Timeout: Regular (Reg.2 Short 0)",null,null],["0041400175",181,8,0,2,"10:34 PM","6:13","SUB: Lee FOR Allen",null,null,null,null],["0041400175",182,1,1,2,"10:35 PM","5:55",null,null,"Leonard 25' 3PT Jump Shot (3 PTS) (Batum 1 AST)","33 - 31","-2"],["0041400175",183,2,1,2,"10:35 PM","5:29","MISS Carter 20' Jump Shot",null,null,null,null],["0041400175",184,4,0,2,"10:35 PM","5:28",null,null,"Batum REBOUND (Off:0 Def:4)",null,null],["0041400175",185,2,86,2,"10:36 PM","5:16",null,null,"MISS Aldridge 12' Turnaround Fadeaway Shot",null,null],["0041400175",186,4,0,2,"10:36 PM","5:14","Calathes REBOUND (Off:0 Def:2)",null,null,null,null],["0041400175",187,2,1,2,"10:36 PM","5:03","MISS Calathes 13' Jump Shot",null,null,null,null],["0041400175",188,4,0,2,"10:36 PM","5:02","Randolph REBOUND (Off:1 Def:2)",null,null,null,null],["0041400175",189,6,2,2,"10:36 PM","4:59",null,null,"Aldridge S.FOUL (P1.T3) (E.Malloy)",null,null],["0041400175",190,3,11,2,"10:36 PM","4:59","Randolph Free Throw 1 of 2 (11 PTS)",null,null,"33 - 32","-1"],["0041400175",192,8,0,2,"10:37 PM","4:59","SUB: Gasol FOR Koufos",null,null,null,null],["0041400175",193,8,0,2,"10:37 PM","4:59",null,null,"SUB: McCollum FOR Afflalo",null,null],["0041400175",194,3,12,2,"10:37 PM","4:59","MISS Randolph Free Throw 2 of 2",null,null,null,null],["0041400175",196,4,0,2,"10:37 PM","4:58","Gasol REBOUND (Off:1 Def:3)",null,null,null,null],["0041400175",197,2,47,2,"10:37 PM","4:48","MISS Randolph 5' Turnaround Jump Shot",null,null,null,null],["0041400175",199,4,0,2,"10:37 PM","4:47","Carter REBOUND (Off:2 Def:0)",null,null,null,null],["0041400175",198,1,92,2,"10:37 PM","4:47","Carter  Putback Slam Dunk (5 PTS)",null,null,"33 - 34","1"],["0041400175",200,5,40,2,"10:38 PM","4:34",null,null,"McCollum Out of Bounds Lost Ball Turnover (P1.T7)",null,null],["0041400175",201,2,1,2,"10:38 PM","4:19","MISS Gasol 21' Jump Shot",null,null,null,null],["0041400175",202,4,0,2,"10:38 PM","4:18",null,null,"Aldridge REBOUND (Off:0 Def:4)",null,null],["0041400175",203,1,5,2,"10:38 PM","4:10",null,null,"Batum 1' Layup (6 PTS)","35 - 34","-1"],["0041400175",204,2,41,2,"10:38 PM","3:59","MISS Calathes 1' Running Layup",null,"Batum BLOCK (1 BLK)",null,null],["0041400175",205,4,0,2,"10:38 PM","3:56","Calathes REBOUND (Off:1 Def:2)",null,null,null,null],["0041400175",206,2,1,2,"10:38 PM","3:52","MISS Lee 21' Jump Shot",null,null,null,null],["0041400175",207,4,0,2,"10:38 PM","3:51",null,null,"Batum REBOUND (Off:0 Def:5)",null,null],["0041400175",208,2,42,2,"10:39 PM","3:43",null,null,"MISS Aldridge  Driving Layup",null,null],["0041400175",209,4,0,2,"10:39 PM","3:39","Gasol REBOUND (Off:1 Def:4)",null,null,null,null],["0041400175",210,1,79,2,"10:39 PM","3:32","Lee 13' Pullup Jump Shot (6 PTS)",null,null,"35 - 36","1"],["0041400175",211,2,1,2,"10:39 PM","3:06",null,null,"MISS Batum  3PT Jump Shot",null,null],["0041400175",212,4,0,2,"10:39 PM","3:05","Randolph REBOUND (Off:1 Def:3)",null,null,null,null],["0041400175",213,1,47,2,"10:39 PM","2:49","Gasol 8' Turnaround Jump Shot (6 PTS)",null,null,"35 - 38","3"],["0041400175",214,9,2,2,"10:40 PM","2:48",null,null,"Trail Blazers Timeout: Short (Reg.2 Short 1)",null,null],["0041400175",216,9,1,2,"10:40 PM","2:48",null,null,null,null,null],["0041400175",217,8,0,2,"10:43 PM","2:48","SUB: Green FOR Calathes",null,null,null,null],["0041400175",219,2,1,2,"10:43 PM","2:34",null,null,"MISS Leonard 25' 3PT Jump Shot",null,null],["0041400175",220,4,0,2,"10:43 PM","2:33","Green REBOUND (Off:0 Def:3)",null,null,null,null],["0041400175",221,2,47,2,"10:44 PM","2:12","MISS Randolph 6' Turnaround Jump Shot",null,null,null,null],["0041400175",222,4,0,2,"10:44 PM","2:09",null,null,"Leonard REBOUND (Off:1 Def:1)",null,null],["0041400175",223,2,1,2,"10:44 PM","1:59",null,null,"MISS Aldridge 15' Jump Shot",null,null],["0041400175",224,4,0,2,"10:44 PM","1:58",null,null,"Lillard REBOUND (Off:1 Def:1)",null,null],["0041400175",225,1,5,2,"10:44 PM","1:55",null,null,"Lillard 2' Layup (11 PTS)","37 - 38","1"],["0041400175",226,1,79,2,"10:44 PM","1:34","Lee 6' Pullup Jump Shot (8 PTS) (Randolph 1 AST)",null,null,"37 - 40","3"],["0041400175",227,2,5,2,"10:45 PM","1:24",null,null,"MISS Batum 1' Layup",null,null],["0041400175",228,4,0,2,"10:45 PM","1:23","Carter REBOUND (Off:2 Def:1)",null,null,null,null],["0041400175",229,1,49,2,"10:45 PM","1:03","Carter  Driving Dunk (7 PTS)",null,null,"37 - 42","5"],["0041400175",230,1,42,2,"10:45 PM","0:42",null,null,"Lillard 1' Driving Layup (13 PTS)","39 - 42","3"],["0041400175",231,1,79,2,"10:46 PM","0:30","Lee 17' Pullup Jump Shot (10 PTS) (Gasol 2 AST)",null,null,"39 - 44","5"],["0041400175",232,2,1,2,"10:46 PM","0:10",null,null,"MISS Batum  3PT Jump Shot",null,null],["0041400175",233,4,0,2,"10:46 PM","0:09","Randolph REBOUND (Off:1 Def:4)",null,null,null,null],["0041400175",234,6,28,2,"10:46 PM","0:05",null,null,"Lillard Personal Take Foul (P1.T4) (E.Malloy)",null,null],["0041400175",235,8,0,2,"10:46 PM","0:05",null,null,"SUB: Lopez FOR Leonard",null,null],["0041400175",236,9,2,2,"10:47 PM","0:05","GRIZZLIES Timeout: Short (Full 2 Short 1)",null,null,null,null],["0041400175",238,6,1,2,"10:48 PM","0:03",null,null,"Lopez P.FOUL (P2.PN) (K.Mauer)",null,null],["0041400175",239,3,11,2,"10:48 PM","0:03","Gasol Free Throw 1 of 2 (7 PTS)",null,null,"39 - 45","6"],["0041400175",241,8,0,2,"10:48 PM","0:03",null,null,"SUB: Leonard FOR Lopez",null,null],["0041400175",242,8,0,2,"10:48 PM","0:03","SUB: Allen FOR Randolph",null,null,null,null],["0041400175",243,3,12,2,"10:48 PM","0:03","Gasol Free Throw 2 of 2 (8 PTS)",null,null,"39 - 46","7"],["0041400175",245,2,1,2,"10:49 PM","0:00",null,null,"MISS McCollum  3PT Jump Shot",null,null],["0041400175",247,4,0,2,"10:49 PM","0:00",null,null,"Trail Blazers Rebound",null,null],["0041400175",246,13,0,2,"10:49 PM","0:00",null,null,null,"39 - 46","7"],["0041400175",249,12,0,3,"11:07 PM","12:00",null,null,null,"39 - 46","7"],["0041400175",250,2,1,3,"11:07 PM","11:46",null,null,"MISS Lillard 27' 3PT Jump Shot",null,null],["0041400175",251,4,0,3,"11:07 PM","11:45","Lee REBOUND (Off:0 Def:1)",null,null,null,null],["0041400175",252,1,1,3,"11:08 PM","11:22","Gasol 21' Jump Shot (10 PTS)",null,null,"39 - 48","9"],["0041400175",253,5,2,3,"11:08 PM","11:16","Lee STEAL (2 STL)",null,"Lillard Lost Ball Turnover (P4.T8)",null,null],["0041400175",254,6,2,3,"11:08 PM","11:14",null,null,"Aldridge S.FOUL (P2.T1) (K.Mauer)",null,null],["0041400175",255,3,11,3,"11:08 PM","11:14","Lee Free Throw 1 of 2 (11 PTS)",null,null,"39 - 49","10"],["0041400175",257,3,12,3,"11:09 PM","11:14","Lee Free Throw 2 of 2 (12 PTS)",null,null,"39 - 50","11"],["0041400175",259,2,41,3,"11:09 PM","11:05",null,null,"MISS Lillard 2' Running Layup",null,null],["0041400175",260,4,0,3,"11:09 PM","11:04","Gasol REBOUND (Off:1 Def:5)",null,null,null,null],["0041400175",261,6,26,3,"11:09 PM","10:58","Lee Offensive Charge Foul (P2.T1) (E.Malloy)",null,null,null,null],["0041400175",262,5,5,3,"11:09 PM","10:58","Lee Foul Turnover (P1.T6)",null,null,null,null],["0041400175",263,2,5,3,"11:10 PM","10:38",null,null,"MISS Aldridge 2' Layup",null,null],["0041400175",264,4,0,3,"11:10 PM","10:37","Allen REBOUND (Off:1 Def:2)",null,null,null,null],["0041400175",265,6,1,3,"11:10 PM","10:31",null,null,"Lopez P.FOUL (P3.T2) (B.Forte)",null,null],["0041400175",266,6,1,3,"11:10 PM","10:23",null,null,"Lopez P.FOUL (P4.T3) (K.Mauer)",null,null],["0041400175",267,1,44,3,"11:11 PM","10:13","Gasol 1' Reverse Layup (12 PTS)",null,null,"39 - 52","13"],["0041400175",268,9,1,3,"11:11 PM","10:11",null,null,"Trail Blazers Timeout: Regular (Reg.3 Short 1)",null,null],["0041400175",270,8,0,3,"11:13 PM","10:11",null,null,"SUB: Leonard FOR Lopez",null,null],["0041400175",271,8,0,3,"11:13 PM","10:11",null,null,"SUB: McCollum FOR Afflalo",null,null],["0041400175",272,1,86,3,"11:15 PM","9:50",null,null,"Aldridge 14' Turnaround Fadeaway (6 PTS)","41 - 52","11"],["0041400175",273,1,49,3,"11:15 PM","9:29","Gasol  Driving Dunk (14 PTS)",null,null,"41 - 54","13"],["0041400175",274,6,14,3,"11:16 PM","9:13","Randolph FLAGRANT.FOUL.TYPE1 (P2.T2) (E.Malloy)",null,null,null,null],["0041400175",275,18,0,3,"11:16 PM","9:13",null,null,null,null,null],["0041400175",276,3,18,3,"11:18 PM","9:13",null,null,"Aldridge Free Throw Flagrant 1 of 2 (7 PTS)","42 - 54","12"],["0041400175",278,3,19,3,"11:18 PM","9:13",null,null,"Aldridge Free Throw Flagrant 2 of 2 (8 PTS)","43 - 54","11"],["0041400175",280,1,1,3,"11:18 PM","9:07",null,null,"Leonard 26' 3PT Jump Shot (6 PTS) (Lillard 1 AST)","46 - 54","8"],["0041400175",281,2,86,3,"11:19 PM","8:40","MISS Gasol 8' Turnaround Fadeaway Shot",null,null,null,null],["0041400175",282,4,0,3,"11:19 PM","8:39",null,null,"Lillard REBOUND (Off:1 Def:2)",null,null],["0041400175",284,1,1,3,"11:19 PM","8:29",null,null,"McCollum 27' 3PT Jump Shot (14 PTS) (Lillard 2 AST)","49 - 54","5"],["0041400175",286,9,1,3,"11:19 PM","8:28","GRIZZLIES Timeout: Regular (Full 3 Short 1)",null,null,null,null],["0041400175",288,1,78,3,"11:23 PM","8:04","Calathes 13' Floating Jump Shot (2 PTS) (Allen 1 AST)",null,null,"49 - 56","7"],["0041400175",289,5,1,3,"11:23 PM","7:51","Allen STEAL (3 STL)",null,"Lillard Bad Pass Turnover (P5.T9)",null,null],["0041400175",290,1,81,3,"11:23 PM","7:41","Lee 15' Pullup Bank Shot (14 PTS) (Allen 2 AST)",null,null,"49 - 58","9"],["0041400175",291,1,1,3,"11:24 PM","7:20",null,null,"Aldridge 20' Jump Shot (10 PTS) (Lillard 3 AST)","51 - 58","7"],["0041400175",292,2,44,3,"11:24 PM","7:01","MISS Lee 1' Reverse Layup",null,"Aldridge BLOCK (2 BLK)",null,null],["0041400175",293,4,0,3,"11:24 PM","7:01","GRIZZLIES Rebound",null,null,null,null],["0041400175",294,2,1,3,"11:24 PM","6:54","MISS Gasol 21' Jump Shot",null,null,null,null],["0041400175",295,4,0,3,"11:24 PM","6:53","GRIZZLIES Rebound",null,null,null,null],["0041400175",296,6,3,3,"11:24 PM","6:53",null,null,"Aldridge L.B.FOUL (P3.T4) (E.Malloy)",null,null],["0041400175",297,2,46,3,"11:25 PM","6:41","MISS Allen 8' Running Jump Shot",null,null,null,null],["0041400175",298,4,0,3,"11:25 PM","6:40",null,null,"Batum REBOUND (Off:0 Def:6)",null,null],["0041400175",299,2,1,3,"11:25 PM","6:29","Allen BLOCK (2 BLK)",null,"MISS Leonard 5' Jump Shot",null,null],["0041400175",300,4,0,3,"11:25 PM","6:29","GRIZZLIES Rebound",null,null,null,null],["0041400175",301,5,1,3,"11:26 PM","6:12","Allen Bad Pass Turnover (P1.T7)",null,null,null,null],["0041400175",302,1,1,3,"11:26 PM","6:05",null,null,"McCollum  3PT Jump Shot (17 PTS) (Batum 2 AST)","54 - 58","4"],["0041400175",303,5,2,3,"11:26 PM","5:40","Gasol Lost Ball Turnover (P2.T8)",null,"Lillard STEAL (1 STL)",null,null],["0041400175",304,6,28,3,"11:26 PM","5:39","Calathes Personal Take Foul (P2.T3) (E.Malloy)",null,null,null,null],["0041400175",305,8,0,3,"11:26 PM","5:39","SUB: Udrih FOR Calathes",null,null,null,null],["0041400175",306,2,71,3,"11:27 PM","5:30",null,null,"MISS Lillard 2' Finger Roll Layup",null,null],["0041400175",307,4,0,3,"11:27 PM","5:27","Gasol REBOUND (Off:1 Def:6)",null,null,null,null],["0041400175",308,2,5,3,"11:27 PM","5:12","MISS Lee 2' Layup",null,null,null,null],["0041400175",309,4,0,3,"11:27 PM","5:11","Gasol REBOUND (Off:2 Def:6)",null,null,null,null],["0041400175",310,2,1,3,"11:27 PM","4:56","MISS Allen  3PT Jump Shot",null,null,null,null],["0041400175",311,4,0,3,"11:27 PM","4:55",null,null,"McCollum REBOUND (Off:0 Def:3)",null,null],["0041400175",312,1,1,3,"11:27 PM","4:48",null,null,"McCollum 25' 3PT Jump Shot (20 PTS)","57 - 58","1"],["0041400175",313,2,1,3,"11:28 PM","4:29","MISS Randolph 21' Jump Shot",null,null,null,null],["0041400175",314,4,0,3,"11:28 PM","4:27",null,null,"Lillard REBOUND (Off:1 Def:3)",null,null],["0041400175",315,6,2,3,"11:28 PM","4:14","Randolph S.FOUL (P3.T4) (K.Mauer)",null,null,null,null],["0041400175",316,3,11,3,"11:28 PM","4:14",null,null,"Aldridge Free Throw 1 of 2 (11 PTS)","58 - 58","TIE"],["0041400175",318,3,12,3,"11:29 PM","4:14",null,null,"MISS Aldridge Free Throw 2 of 2",null,null],["0041400175",320,4,0,3,"11:29 PM","4:13","Allen REBOUND (Off:1 Def:3)",null,null,null,null],["0041400175",321,2,1,3,"11:29 PM","3:54","MISS Udrih 25' 3PT Jump Shot",null,null,null,null],["0041400175",322,4,0,3,"11:29 PM","3:53",null,null,"Batum REBOUND (Off:0 Def:7)",null,null],["0041400175",323,5,2,3,"11:29 PM","3:51","Allen STEAL (4 STL)",null,"Batum Lost Ball Turnover (P1.T10)",null,null],["0041400175",324,6,4,3,"11:29 PM","3:51","Gasol OFF.Foul (P2) (K.Mauer)",null,null,null,null],["0041400175",325,5,5,3,"11:29 PM","3:51","Gasol Foul Turnover (P3.T9)",null,null,null,null],["0041400175",326,1,1,3,"11:30 PM","3:39",null,null,"McCollum 26' 3PT Jump Shot (23 PTS) (Batum 3 AST)","61 - 58","-3"],["0041400175",328,9,1,3,"11:30 PM","3:36","GRIZZLIES Timeout: Regular (Full 4 Short 1)",null,null,null,null],["0041400175",329,2,47,3,"11:32 PM","3:19","MISS Randolph 4' Turnaround Jump Shot",null,null,null,null],["0041400175",331,4,0,3,"11:32 PM","3:18","Allen REBOUND (Off:2 Def:3)",null,null,null,null],["0041400175",330,1,4,3,"11:32 PM","3:18","Allen 1' Tip Shot (8 PTS)",null,null,"61 - 60","-1"],["0041400175",332,2,5,3,"11:32 PM","3:09",null,null,"MISS Aldridge 1' Layup",null,null],["0041400175",334,4,0,3,"11:33 PM","3:08",null,null,"Batum REBOUND (Off:1 Def:7)",null,null],["0041400175",333,2,4,3,"11:33 PM","3:08",null,null,"MISS Batum 1' Tip Shot",null,null],["0041400175",335,4,0,3,"11:33 PM","3:05","Gasol REBOUND (Off:2 Def:7)",null,null,null,null],["0041400175",336,1,1,3,"11:33 PM","2:56","Gasol 18' Jump Shot (16 PTS) (Allen 3 AST)",null,null,"61 - 62","1"],["0041400175",337,6,1,3,"11:33 PM","2:35","Udrih P.FOUL (P3.PN) (E.Malloy)",null,null,null,null],["0041400175",338,5,2,3,"11:34 PM","2:33","Allen STEAL (5 STL)",null,"Lillard Lost Ball Turnover (P6.T11)",null,null],["0041400175",339,2,5,3,"11:34 PM","2:29","MISS Udrih 1' Layup",null,null,null,null],["0041400175",340,4,0,3,"11:34 PM","2:26","Allen REBOUND (Off:3 Def:3)",null,null,null,null],["0041400175",341,6,4,3,"11:34 PM","2:14","Randolph OFF.Foul (P4) (E.Malloy)",null,null,null,null],["0041400175",342,5,5,3,"11:34 PM","2:14","Randolph Foul Turnover (P2.T10)",null,null,null,null],["0041400175",343,6,11,3,"11:34 PM","2:14","Randolph T.FOUL (P4.PN) (B.Forte)",null,null,null,null],["0041400175",344,18,2,3,"11:35 PM","2:14",null,null,null,"61 - 62","1"],["0041400175",346,3,16,3,"11:37 PM","2:14",null,null,"Lillard Free Throw Technical (14 PTS)","62 - 62","TIE"],["0041400175",355,8,0,3,"11:37 PM","2:14","SUB: Green FOR Randolph",null,null,null,null],["0041400175",348,2,1,3,"11:37 PM","2:03",null,null,"MISS Lillard 28' 3PT Jump Shot",null,null],["0041400175",349,4,0,3,"11:37 PM","2:02","Gasol REBOUND (Off:2 Def:8)",null,null,null,null],["0041400175",350,5,4,3,"11:37 PM","1:50","Lee Traveling Turnover (P2.T11)",null,null,null,null],["0041400175",351,7,5,3,"11:38 PM","1:38","Allen Violation:Kicked Ball (.)",null,null,null,null],["0041400175",352,2,5,3,"11:38 PM","1:28",null,null,"MISS Aldridge  Layup",null,null],["0041400175",353,4,0,3,"11:38 PM","1:27","Udrih REBOUND (Off:0 Def:2)",null,null,null,null],["0041400175",354,6,2,3,"11:39 PM","1:13",null,null,"Aldridge S.FOUL (P4.PN) (B.Forte)",null,null],["0041400175",356,3,11,3,"11:39 PM","1:13","Green Free Throw 1 of 2 (1 PTS)",null,null,"62 - 63","1"],["0041400175",358,8,0,3,"11:39 PM","1:13",null,null,"SUB: Lopez FOR Aldridge",null,null],["0041400175",359,3,12,3,"11:39 PM","1:13","Green Free Throw 2 of 2 (2 PTS)",null,null,"62 - 64","2"],["0041400175",361,2,1,3,"11:40 PM","0:54",null,null,"MISS McCollum 26' 3PT Jump Shot",null,null],["0041400175",362,4,0,3,"11:40 PM","0:53","Green REBOUND (Off:0 Def:4)",null,null,null,null],["0041400175",363,1,5,3,"11:40 PM","0:45","Lee 1' Layup (16 PTS)",null,null,"62 - 66","4"],["0041400175",364,1,42,3,"11:40 PM","0:36",null,null,"McCollum 1' Driving Layup (25 PTS)","64 - 66","2"],["0041400175",365,1,1,3,"11:40 PM","0:25","Gasol 13' Jump Shot (18 PTS) (Udrih 1 AST)",null,null,"64 - 68","4"],["0041400175",366,1,79,3,"11:41 PM","0:02",null,null,"McCollum 20' Pullup Jump Shot (27 PTS)","66 - 68","2"],["0041400175",367,2,1,3,"11:41 PM","0:00","MISS Green 41' 3PT Jump Shot",null,null,null,null],["0041400175",369,4,0,3,"11:41 PM","0:00","GRIZZLIES Rebound",null,null,null,null],["0041400175",368,13,0,3,"11:41 PM","0:00",null,null,null,"66 - 68","2"],["0041400175",371,12,0,4,"11:45 PM","12:00",null,null,null,"66 - 68","2"],["0041400175",372,1,56,4,"11:45 PM","11:40","Gasol 5' Running Hook Shot (20 PTS)",null,null,"66 - 70","4"],["0041400175",373,1,3,4,"11:45 PM","11:20",null,null,"Lopez 6' Hook Shot (2 PTS) (Batum 4 AST)","68 - 70","2"],["0041400175",374,2,1,4,"11:46 PM","10:53","MISS Gasol 19' Jump Shot",null,null,null,null],["0041400175",375,4,0,4,"11:46 PM","10:51","Udrih REBOUND (Off:1 Def:2)",null,null,null,null],["0041400175",376,2,79,4,"11:46 PM","10:44","MISS Udrih 20' Pullup Jump Shot",null,null,null,null],["0041400175",377,4,0,4,"11:46 PM","10:42",null,null,"Lillard REBOUND (Off:1 Def:4)",null,null],["0041400175",378,2,41,4,"11:46 PM","10:26",null,null,"MISS McCollum 2' Running Layup",null,null],["0041400175",379,4,0,4,"11:46 PM","10:24","Gasol REBOUND (Off:2 Def:9)",null,null,null,null],["0041400175",380,6,2,4,"11:46 PM","10:21",null,null,"Leonard S.FOUL (P3.T1) (B.Forte)",null,null],["0041400175",381,3,11,4,"11:47 PM","10:21","Green Free Throw 1 of 2 (3 PTS)",null,null,"68 - 71","3"],["0041400175",383,3,12,4,"11:47 PM","10:21","Green Free Throw 2 of 2 (4 PTS)",null,null,"68 - 72","4"],["0041400175",385,1,5,4,"11:47 PM","10:05",null,null,"Lillard 1' Layup (16 PTS)","70 - 72","2"],["0041400175",386,2,44,4,"11:48 PM","9:41","MISS Green  Reverse Layup",null,null,null,null],["0041400175",387,4,0,4,"11:48 PM","9:40",null,null,"Leonard REBOUND (Off:1 Def:2)",null,null],["0041400175",388,2,5,4,"11:48 PM","9:28",null,null,"MISS McCollum 2' Layup",null,null],["0041400175",389,4,0,4,"11:48 PM","9:27","Green REBOUND (Off:0 Def:5)",null,null,null,null],["0041400175",390,2,1,4,"11:48 PM","9:10","MISS Udrih  3PT Jump Shot",null,null,null,null],["0041400175",391,4,0,4,"11:48 PM","9:09",null,null,"Batum REBOUND (Off:1 Def:8)",null,null],["0041400175",392,6,2,4,"11:49 PM","9:00","Gasol S.FOUL (P3.T1) (B.Forte)",null,null,null,null],["0041400175",395,3,11,4,"11:49 PM","9:00",null,null,"Lopez Free Throw 1 of 2 (3 PTS)","71 - 72","1"],["0041400175",393,8,0,4,"11:49 PM","9:00","SUB: Calathes FOR Udrih",null,null,null,null],["0041400175",394,8,0,4,"11:49 PM","9:00","SUB: Randolph FOR Gasol",null,null,null,null],["0041400175",397,8,0,4,"11:49 PM","9:00",null,null,"SUB: Aldridge FOR Leonard",null,null],["0041400175",398,3,12,4,"11:49 PM","9:00",null,null,"Lopez Free Throw 2 of 2 (4 PTS)","72 - 72","TIE"],["0041400175",400,2,5,4,"11:50 PM","8:45","MISS Carter 3' Layup",null,"Lopez BLOCK (2 BLK)",null,null],["0041400175",401,4,0,4,"11:50 PM","8:42",null,null,"Batum REBOUND (Off:1 Def:9)",null,null],["0041400175",402,5,2,4,"11:50 PM","8:41","Carter STEAL (1 STL)",null,"Batum Lost Ball Turnover (P2.T12)",null,null],["0041400175",403,1,63,4,"11:50 PM","8:39","Carter 6' Fadeaway Jumper (9 PTS) (Allen 4 AST)",null,null,"72 - 74","2"],["0041400175",404,2,1,4,"11:50 PM","8:14",null,null,"MISS Batum 28' 3PT Jump Shot",null,null],["0041400175",405,4,0,4,"11:50 PM","8:13","Allen REBOUND (Off:3 Def:4)",null,null,null,null],["0041400175",406,2,5,4,"11:51 PM","7:59","MISS Randolph 2' Layup",null,"Lopez BLOCK (3 BLK)",null,null],["0041400175",407,4,0,4,"11:51 PM","7:58","GRIZZLIES Rebound",null,null,null,null],["0041400175",408,9,1,4,"11:51 PM","7:58",null,null,null,null,null],["0041400175",410,8,0,4,"11:54 PM","7:58","SUB: Koufos FOR Allen",null,null,null,null],["0041400175",411,2,71,4,"11:54 PM","7:52","MISS Green 1' Finger Roll Layup",null,null,null,null],["0041400175",412,4,0,4,"11:54 PM","7:50","Randolph REBOUND (Off:2 Def:4)",null,null,null,null],["0041400175",413,1,1,4,"11:54 PM","7:49","Randolph 6' Jump Shot (13 PTS)",null,null,"72 - 76","4"],["0041400175",414,1,5,4,"11:54 PM","7:28",null,null,"Aldridge 2' Layup (13 PTS)","74 - 76","2"],["0041400175",415,6,2,4,"11:54 PM","7:28","Calathes S.FOUL (P3.T2) (K.Mauer)",null,null,null,null],["0041400175",416,3,10,4,"11:55 PM","7:28",null,null,"Aldridge Free Throw 1 of 1 (14 PTS)","75 - 76","1"],["0041400175",418,2,46,4,"11:55 PM","7:11","MISS Randolph 4' Running Jump Shot",null,null,null,null],["0041400175",419,4,0,4,"11:55 PM","7:09",null,null,"Aldridge REBOUND (Off:0 Def:5)",null,null],["0041400175",420,2,46,4,"11:55 PM","6:56",null,null,"MISS Aldridge 8' Running Jump Shot",null,null],["0041400175",421,4,0,4,"11:55 PM","6:54","Randolph REBOUND (Off:2 Def:5)",null,null,null,null],["0041400175",422,2,5,4,"11:56 PM","6:40","MISS Calathes 3' Layup",null,null,null,null],["0041400175",423,4,0,4,"11:56 PM","6:39",null,null,"Lopez REBOUND (Off:0 Def:4)",null,null],["0041400175",424,2,1,4,"11:56 PM","6:23",null,null,"MISS Lillard 25' 3PT Jump Shot",null,null],["0041400175",425,4,0,4,"11:56 PM","6:23","Koufos REBOUND (Off:4 Def:3)",null,null,null,null],["0041400175",426,2,1,4,"11:56 PM","6:03","MISS Carter  3PT Jump Shot",null,null,null,null],["0041400175",427,4,0,4,"11:56 PM","6:02",null,null,"Aldridge REBOUND (Off:0 Def:6)",null,null],["0041400175",428,2,79,4,"11:56 PM","5:53",null,null,"MISS Batum 20' Pullup Jump Shot",null,null],["0041400175",429,4,0,4,"11:57 PM","5:52","Carter REBOUND (Off:2 Def:2)",null,null,null,null],["0041400175",430,1,5,4,"11:57 PM","5:37","Calathes 2' Layup (4 PTS) (Randolph 2 AST)",null,null,"75 - 78","3"],["0041400175",431,9,1,4,"11:57 PM","5:36",null,null,"Trail Blazers Timeout: Regular (Reg.4 Short 1)",null,null],["0041400175",433,8,0,4,"12:00 AM","5:36",null,null,"SUB: Leonard FOR Lopez",null,null],["0041400175",434,8,0,4,"12:00 AM","5:36","SUB: Gasol FOR Koufos",null,null,null,null],["0041400175",435,5,1,4,"12:01 AM","5:13",null,null,"McCollum Bad Pass Turnover (P2.T13)",null,null],["0041400175",436,1,79,4,"12:01 AM","5:00","Green 16' Pullup Jump Shot (6 PTS) (Gasol 3 AST)",null,null,"75 - 80","5"],["0041400175",437,2,1,4,"12:02 AM","4:48",null,null,"MISS McCollum 26' 3PT Jump Shot",null,null],["0041400175",438,4,0,4,"12:02 AM","4:47","Carter REBOUND (Off:2 Def:3)",null,null,null,null],["0041400175",439,2,1,4,"12:02 AM","4:30","MISS Gasol 18' Jump Shot",null,null,null,null],["0041400175",440,4,0,4,"12:02 AM","4:27",null,null,"Lillard REBOUND (Off:1 Def:5)",null,null],["0041400175",441,6,1,4,"12:02 AM","4:21","Calathes P.FOUL (P4.T3) (K.Mauer)",null,null,null,null],["0041400175",442,8,0,4,"12:02 AM","4:21","SUB: Lee FOR Carter",null,null,null,null],["0041400175",443,2,5,4,"12:03 AM","4:14","Green BLOCK (1 BLK)",null,"MISS Aldridge 1' Layup",null,null],["0041400175",444,4,0,4,"12:03 AM","4:12","Gasol REBOUND (Off:2 Def:10)",null,null,null,null],["0041400175",445,1,42,4,"12:03 AM","3:54","Green 1' Driving Layup (8 PTS)",null,null,"75 - 82","7"],["0041400175",446,6,2,4,"12:03 AM","3:54",null,null,"Leonard S.FOUL (P4.T2) (K.Mauer)",null,null],["0041400175",447,3,10,4,"12:03 AM","3:54","Green Free Throw 1 of 1 (9 PTS)",null,null,"75 - 83","8"],["0041400175",449,2,80,4,"12:04 AM","3:44",null,null,"MISS Lillard 26' 3PT Step Back Jump Shot",null,null],["0041400175",450,4,0,4,"12:04 AM","3:41","Calathes REBOUND (Off:1 Def:3)",null,null,null,null],["0041400175",451,1,1,4,"12:04 AM","3:27","Randolph 13' Jump Shot (15 PTS)",null,null,"75 - 85","10"],["0041400175",452,9,1,4,"12:04 AM","3:26",null,null,"Trail Blazers Timeout: Regular (Reg.5 Short 1)",null,null],["0041400175",454,1,1,4,"12:08 AM","3:16",null,null,"Leonard 25' 3PT Jump Shot (9 PTS) (Batum 5 AST)","78 - 85","7"],["0041400175",456,1,1,4,"12:08 AM","2:51","Lee 15' Jump Shot (18 PTS) (Green 1 AST)",null,null,"78 - 87","9"],["0041400175",457,2,5,4,"12:08 AM","2:39",null,null,"MISS Aldridge  Layup",null,null],["0041400175",458,4,0,4,"12:09 AM","2:36","Gasol REBOUND (Off:2 Def:11)",null,null,null,null],["0041400175",459,2,42,4,"12:09 AM","2:21","MISS Randolph 2' Driving Layup",null,null,null,null],["0041400175",460,4,0,4,"12:09 AM","2:18",null,null,"Leonard REBOUND (Off:1 Def:3)",null,null],["0041400175",461,2,1,4,"12:09 AM","2:10",null,null,"MISS Leonard 27' 3PT Jump Shot",null,null],["0041400175",462,4,0,4,"12:09 AM","2:09",null,null,"Aldridge REBOUND (Off:1 Def:6)",null,null],["0041400175",463,2,3,4,"12:09 AM","2:06",null,null,"MISS Aldridge 5' Hook Shot",null,null],["0041400175",464,4,0,4,"12:09 AM","2:04","Gasol REBOUND (Off:2 Def:12)",null,null,null,null],["0041400175",465,1,80,4,"12:09 AM","1:43","Calathes 19' Step Back Jump Shot (6 PTS)",null,null,"78 - 89","11"],["0041400175",466,6,1,4,"12:10 AM","1:36","Randolph P.FOUL (P5.T4) (E.Malloy)",null,null,null,null],["0041400175",467,1,1,4,"12:10 AM","1:31",null,null,"McCollum 30' 3PT Jump Shot (30 PTS) (Batum 6 AST)","81 - 89","8"],["0041400175",468,6,28,4,"12:10 AM","1:27",null,null,"Batum Personal Take Foul (P1.T3) (B.Forte)",null,null],["0041400175",469,2,1,4,"12:11 AM","1:16","MISS Green 25' 3PT Jump Shot",null,null,null,null],["0041400175",470,4,0,4,"12:11 AM","1:16",null,null,"Trail Blazers Rebound",null,null],["0041400175",471,2,79,4,"12:11 AM","1:08",null,null,"MISS McCollum 14' Pullup Jump Shot",null,null],["0041400175",472,4,0,4,"12:11 AM","1:08",null,null,"Trail Blazers Rebound",null,null],["0041400175",473,8,0,4,"12:11 AM","1:08","SUB: Allen FOR Calathes",null,null,null,null],["0041400175",474,2,1,4,"12:12 AM","1:04",null,null,"MISS Batum  3PT Jump Shot",null,null],["0041400175",475,4,0,4,"12:12 AM","1:04","Green REBOUND (Off:0 Def:6)",null,null,null,null],["0041400175",476,6,28,4,"12:12 AM","1:04",null,null,"McCollum Personal Take Foul (P2.PN) (K.Mauer)",null,null],["0041400175",477,3,11,4,"12:12 AM","1:04","MISS Green Free Throw 1 of 2",null,null,null,null],["0041400175",478,4,1,4,"12:12 AM","1:04","GRIZZLIES Rebound",null,null,null,null],["0041400175",479,3,12,4,"12:12 AM","1:04","Green Free Throw 2 of 2 (10 PTS)",null,null,"81 - 90","9"],["0041400175",482,9,1,4,"12:13 AM","1:04",null,null,"Trail Blazers Timeout: Regular (Reg.6 Short 1)",null,null],["0041400175",483,2,1,4,"12:15 AM","0:59",null,null,"MISS McCollum 26' 3PT Jump Shot",null,null],["0041400175",484,4,0,4,"12:15 AM","0:58","Randolph REBOUND (Off:2 Def:6)",null,null,null,null],["0041400175",485,6,28,4,"12:15 AM","0:57",null,null,"Lillard Personal Take Foul (P2.PN) (B.Forte)",null,null],["0041400175",486,3,11,4,"12:15 AM","0:57","Randolph Free Throw 1 of 2 (16 PTS)",null,null,"81 - 91","10"],["0041400175",488,3,12,4,"12:16 AM","0:57","MISS Randolph Free Throw 2 of 2",null,null,null,null],["0041400175",490,4,0,4,"12:16 AM","0:56",null,null,"Aldridge REBOUND (Off:1 Def:7)",null,null],["0041400175",491,2,80,4,"12:16 AM","0:48",null,null,"MISS Lillard 27' 3PT Step Back Jump Shot",null,null],["0041400175",492,4,0,4,"12:16 AM","0:45",null,null,"Aldridge REBOUND (Off:2 Def:7)",null,null],["0041400175",493,1,80,4,"12:16 AM","0:43",null,null,"McCollum  3PT Step Back Jump Shot (33 PTS) (Leonard 1 AST)","84 - 91","7"],["0041400175",494,6,28,4,"12:16 AM","0:42",null,null,"Aldridge Personal Take Foul (P5.PN) (K.Mauer)",null,null],["0041400175",495,3,11,4,"12:17 AM","0:42","Gasol Free Throw 1 of 2 (21 PTS)",null,null,"84 - 92","8"],["0041400175",497,3,12,4,"12:17 AM","0:42","Gasol Free Throw 2 of 2 (22 PTS)",null,null,"84 - 93","9"],["0041400175",499,6,2,4,"12:17 AM","0:36","Allen S.FOUL (P2.PN) (K.Mauer)",null,null,null,null],["0041400175",500,3,11,4,"12:18 AM","0:36",null,null,"MISS Lillard Free Throw 1 of 2",null,null],["0041400175",501,4,1,4,"12:18 AM","0:36",null,null,"Trail Blazers Rebound",null,null],["0041400175",502,8,0,4,"12:18 AM","0:36","SUB: Carter FOR Allen",null,null,null,null],["0041400175",503,3,12,4,"12:18 AM","0:36",null,null,"Lillard Free Throw 2 of 2 (17 PTS)","85 - 93","8"],["0041400175",505,6,28,4,"12:19 AM","0:36",null,null,"Leonard Personal Take Foul (P5.PN) (E.Malloy)",null,null],["0041400175",506,3,11,4,"12:19 AM","0:36","MISS Gasol Free Throw 1 of 2",null,null,null,null],["0041400175",507,4,1,4,"12:19 AM","0:36","GRIZZLIES Rebound",null,null,null,null],["0041400175",508,8,0,4,"12:19 AM","0:36","SUB: Allen FOR Carter",null,null,null,null],["0041400175",509,3,12,4,"12:19 AM","0:36","Gasol Free Throw 2 of 2 (23 PTS)",null,null,"85 - 94","9"],["0041400175",512,9,2,4,"12:20 AM","0:36",null,null,"Trail Blazers Timeout: Short (Reg.6 Short 2)",null,null],["0041400175",513,1,71,4,"12:21 AM","0:32",null,null,"Lillard 1' Finger Roll Layup (19 PTS)","87 - 94","7"],["0041400175",514,9,2,4,"12:21 AM","0:32","GRIZZLIES Timeout: Short (Full 4 Short 2)",null,null,null,null],["0041400175",516,8,0,4,"12:22 AM","0:32",null,null,"SUB: Blake FOR Leonard",null,null],["0041400175",517,8,0,4,"12:22 AM","0:32","SUB: Carter FOR Allen",null,null,null,null],["0041400175",518,6,28,4,"12:23 AM","0:31",null,null,"Aldridge Personal Take Foul (P6.PN) (E.Malloy)",null,null],["0041400175",519,8,0,4,"12:23 AM","0:31",null,null,"SUB: Leonard FOR Aldridge",null,null],["0041400175",520,3,11,4,"12:23 AM","0:31","MISS Gasol Free Throw 1 of 2",null,null,null,null],["0041400175",521,4,1,4,"12:23 AM","0:31","GRIZZLIES Rebound",null,null,null,null],["0041400175",522,8,0,4,"12:23 AM","0:31","SUB: Allen FOR Randolph",null,null,null,null],["0041400175",523,3,12,4,"12:23 AM","0:31","Gasol Free Throw 2 of 2 (24 PTS)",null,null,"87 - 95","8"],["0041400175",525,1,79,4,"12:24 AM","0:25",null,null,"Lillard 27' 3PT Pullup Jump Shot (22 PTS)","90 - 95","5"],["0041400175",526,6,28,4,"12:24 AM","0:24",null,null,"Leonard Personal Take Foul (P6.PN) (B.Forte)",null,null],["0041400175",527,8,0,4,"12:25 AM","0:24",null,null,"SUB: Frazier FOR Leonard",null,null],["0041400175",528,3,11,4,"12:25 AM","0:24","Gasol Free Throw 1 of 2 (25 PTS)",null,null,"90 - 96","6"],["0041400175",530,3,12,4,"12:25 AM","0:24","Gasol Free Throw 2 of 2 (26 PTS)",null,null,"90 - 97","7"],["0041400175",532,1,1,4,"12:26 AM","0:15",null,null,"Blake 27' 3PT Jump Shot (5 PTS) (Batum 7 AST)","93 - 97","4"],["0041400175",533,6,28,4,"12:26 AM","0:14",null,null,"Blake Personal Take Foul (P1.PN) (E.Malloy)",null,null],["0041400175",534,3,11,4,"12:26 AM","0:14","Lee Free Throw 1 of 2 (19 PTS)",null,null,"93 - 98","5"],["0041400175",536,3,12,4,"12:26 AM","0:14","Lee Free Throw 2 of 2 (20 PTS)",null,null,"93 - 99","6"],["0041400175",538,2,1,4,"12:27 AM","0:06","Gasol BLOCK (2 BLK)",null,"MISS Batum 19' Jump Shot",null,null],["0041400175",539,4,0,4,"12:27 AM","0:04","Green REBOUND (Off:0 Def:7)",null,null,null,null],["0041400175",541,13,0,4,"12:27 AM","0:00",null,null,null,"93 - 99","6"]]},{"name":"AvailableVideo","headers":["VIDEO_AVAILABLE_FLAG"],"rowSet":[[1]]}]}